{"data":[{"空太郎":"「ほら、お前ら飯だぞー」"},{"ガァコ's":"「ガァッ！　ガァッ！」"},{"空太郎":"「いっぱい食べて強く育てよ」"},{"華子":"「はい。水も替えてあげたわよ」"},{"ガァコ's":"「ガァ～」"},{"華子":"「はいはい。まずはご飯からよ」"},{"空太郎":"　近寄ってくるガァコの頭を一撫でして、[r]　こっちにやってくる。"},{"空太郎":"「お疲れさん。付き合ってもらって悪いな」"},{"空太郎":"　今日の朝当番は俺だけど、[r]　華子も付き合ってくれていた。"},{"空太郎":"　朝に弱い華子にしては、かなり珍しい。"},{"華子":"「ま、あんまりわたしはガァコたちの世話やってないからね。[r]　これぐらいやらないと」"},{"華子":"「はあ～、いい食べっぷり。[r]　わたしまでお腹すいてきちゃう」"},{"空太郎":"「お前……あれはガァコたちのエサだからな？」"},{"華子":"「馬鹿、たべないわよ」"},{"空太郎":"　くだらない冗談を言って、笑い合う。"},{"華子":"「あとは……なにかすることあったっけ？」"},{"空太郎":"「いや、もう全部済ませたよ」"},{"華子":"「それならちょっと部室に行きましょ？」"},{"空太郎":"「生物部か？」"},{"華子":"「ううん、映画部の方」"},{"空太郎":"「？」"},{"空太郎":"　何するんだ？"},{"華子":"「この前の点検の映像、ちょっと見て欲しいのよ」"},{"空太郎":"「ああ、あれか」"},{"空太郎":"　先週あたりに、[r]　月ヶ瀬のプリフライトチェックを撮ったやつだ。"},{"華子":"「わたしもちょっと調べて作ってみたけど、[r]　間違ってるところもあるかもしれないからさ」"},{"空太郎":"「はは。わかった、行こうか」"},{"華子":"「これなんだけどね」"},{"空太郎":"　移動して準備を終えた華子が、[r]　さっそく映像を流し始める。"},{"空太郎":"　画面上には、ＭＸⅡの周りで声を出して点検している[r]　月ヶ瀬の姿が映っている。"},{"空太郎":"　邪魔にならない程度に字幕が被せてあって、[r]　そこでは簡単な補足説明がされていた。"},{"空太郎":"「ふむふむ……なるほどな」"},{"空太郎":"　簡潔ながら、わかりやすい説明だ。[r]　これなら必要十分な情報量だろう。"},{"空太郎":"「うん、いいんじゃないか？」"},{"空太郎":"　しばらく見た上で、華子に頷いてみせる。"},{"空太郎":"「……あ、でもこれ、字幕だけなのか？[r]　ナレーションとか入れても良さそうだけど」"},{"華子":"「え？　あー……どうしよう。考えてなかったわ」"},{"空太郎":"　その手があったか……とうんうん唸る華子。"},{"華子":"「んー……亜美にお願いしようかしら」"},{"空太郎":"「華子はやらないのか」"},{"華子":"「前も言ったでしょ？　監督はでしゃばらない、よ」"},{"空太郎":"「とか言って、恥ずかしいんだろ」"},{"華子":"「それもあるけど……亜美も部長でしょう？[r]　ある程度、前に出ないといけないわ」"},{"空太郎":"「ふむ……そういうことにしとこうか」"},{"華子":"「あとで亜美にお願いしに行きましょ」"},{"空太郎":"「そうだな。でも椿、引き受けてくれるかな」"},{"空太郎":"　こういうの、苦手そうだ。"},{"華子":"「ちょっと気弱ではあるけど、責任感の強い子よ。[r]　きっと頷いてくれるわ」"},{"空太郎":"「……う～ん」"},{"空太郎":"　自信ありげな華子にどこか不安を覚えつつ、[r]　ＨＲの時間まで映像を見続けていた。"},{"空太郎":"　――放課後、バイクでの訓練も終えて。"},{"空太郎":"　滑走路から部室に戻り、今日も解散というところで、[r]　華子が今朝のことを口にした。"},{"華子":"「実はね。ちょっと亜美にお願いがあるのよ」"},{"亜美":"「ええ？　わたしに？」"},{"華子":"「そ。亜美さ、ナレーションやらない？」"},{"亜美":"「え？　ええっ！？　ナレーションって映画の？」"},{"華子":"「そうよ。正確にはドキュメンタリー映画の、だけど」"},{"亜美":"「む、無理！　恥ずかしすぎるよ～！」"},{"空太郎":"　手をワタワタさせて慌てる椿だけど、[r]　華子は引き下がらない。"},{"華子":"「平気よ。だって、録音した音声を映像にのせるだけ。[r]　別に顔を出すわけじゃないんだから」"},{"亜美":"「そ、そうだけど……」"},{"華子":"「今回の映画は、生物部主導の３つの部活共同作品よ」"},{"華子":"「そして、ガンっていう生き物を扱う以上、[r]　生物部の重きは大きいわ」"},{"華子":"「ここでガツンとアピールして、[r]　生物部に部員を集めちゃいましょ？」"},{"空太郎":"　……なるほど、そういうことか。"},{"空太郎":"　椿に無理させてまで任せようとしているのは、[r]　これからの椿自身のためでもあったのか。"},{"亜美":"「ぶ、部員……」"},{"華子":"「そうよ。私たちもそうだけど、[r]　来年以降、存続させるためには新入部員が必須よ」"},{"亜美":"「た、たしかに……」"},{"華子":"「飛行機部の魅力はウルトラ・ライトの飛行風景で。[r]　映画部は、ドキュメンタリーのクオリティーで」"},{"華子":"「そして生物部は、ガァコたちの世話の様子や、[r]　生態をナレーションとして流す」"},{"華子":"「元々、ガァコたちの可愛さはピーコ時代にしっかり浸透してる。[r]　そこと生物部の魅力をしっかり絡めたナレーションを作るの」"},{"亜美":"「う、うん……」"},{"華子":"「そしたら来年以降もきちんと世話が出来るし、[r]　部費もきちんと集まって、さらに発展していけるわ」"},{"華子":"「そうすれば、来年も亜美は寂しくないでしょ？」"},{"亜美":"「華子姉……」"},{"空太郎":"　そうだ。俺たちはやがて卒業してしまう。"},{"空太郎":"　そうしたら生物部は元通り、椿ただ１人。[r]　あの部室で１人の部活になってしまう。"},{"空太郎":"　膨らんでしまった活動をこなすのも大変だし、[r]　何より……寂しいはずだ。"},{"まひる":"「やりましょう、亜美」"},{"ひかり":"「そうよ椿さん。せっかくのチャンスじゃない」"},{"空太郎":"　話を聞いていた月ヶ瀬と桐見も、[r]　華子の意図を汲み取って、椿を説得にかかった。"},{"空太郎":"「椿、やってみないか？」"},{"亜美":"「みんな……う、うん」"},{"亜美":"「華子姉。わたし、やるよ」"},{"華子":"「そっか。ありがとう、亜美」"},{"空太郎":"　真剣な顔で頷く椿に、華子は安心したような笑みを見せた。"},{"空太郎":"　そんな様子を傍らで見ていたピヨコが、[r]　元気に飛び跳ねて宣言する。"},{"ピヨコ":"「ピヨコが、ここに入学したら生物部部長やるの！」"},{"まひる":"「なるほど。部長予約ですね。[r]　ですが、部長への道は優しくないですよ？」"},{"まひる":"「ピヨコが入るころには、生物部は水鳥自然教育学園で[r]　１番大きな部活になっているでしょうから」"},{"ピヨコ":"「お～～っ！　ピヨコ頑張るっ！！」"},{"空太郎":"「ははは」"},{"ピヨコ":"「ピヨコの生物部部長就任の暁には、[r]　ヒコ～ショウネンの特別フライトを要求するの！」"},{"空太郎":"「はは。なら、隣に乗せられるように[r]　それまでに教証を取っておかないとだな」"},{"華子":"「これで……あとは、ちゃんと飛ぶだけね」"},{"空太郎":"「……そうだな」"},{"空太郎":"　ガァコたちは一緒についてくるようにはなったけど、[r]　編隊飛行にはまだ挑戦できてもいない。"},{"空太郎":"　今月末までで、編隊飛行をマスターして[r]　モルゲンロートをバックにした撮影を成功させる必要がある。"},{"華子":"「感動するようなモルゲンロートの飛行を期待しておくわ」"},{"空太郎":"「……ああ、任せとけ」"},{"空太郎":"　ガァコたちの未来と、それぞれの部活の存続。"},{"空太郎":"　どれも大事なものだけど、それを背負って飛べるのは、[r]　きっと凄く名誉なことだと思う。"},{"空太郎":"　みんなのためにも、飛んでみせなければ。"},{"華子":"「う～ん……[r]　えっと、『これは、ちょうど孵卵器に入れて、[r]　１週間後の映像です』……と」"},{"華子":"「『光を当てて透過させてみると、卵内の雛の様子が見えます』」"},{"華子":"「『ここが、心臓の位置です……』[r]　ん～……このあたりまでやり出すと長くなるか……カットね」"},{"空太郎":"「なあ、華子」"},{"華子":"「ん～？　なに～？」"},{"空太郎":"「なんで俺の背中を背もたれにして作業してんの？」"},{"華子":"「ちょうどいいところに背中があったからね～」"},{"空太郎":"「……まあ、いいんだけどさ」"},{"華子":"「あら、素直」"},{"空太郎":"「華子とくっついてるのは、悪い気分じゃないし」"},{"空太郎":"　背中に感じる体温。首筋をくすぐる髪。[r]　その全部が好きな女の子のものなんだから、[r]　嫌なわけがない。"},{"空太郎":"　それに、これだけ無防備でいられるってことは、[r]　俺に気を許してくれている証明でもある。"},{"華子":"「ふふっ。まあ、わたしなりのご褒美かしらね」"},{"空太郎":"　最近は特に頑張ってるし、と言って笑う華子。"},{"空太郎":"　でも、なんでだろう。[r]　どこか元気がないような気がした。"},{"空太郎":"「……華子、どうかしたのか？」"},{"空太郎":"　思い切って尋ねてみた。[r]　少しの間を置いて、華子は口を開く。"},{"華子":"「わたしも技量認定証、取ればよかったかしら」"},{"空太郎":"「え？　なんでだ？」"},{"華子":"「そしたら、わたしも隣に乗れるじゃない」"},{"空太郎":"「お前……もしかして妬いてるのか？」"},{"華子":"「そうかもね～……」"},{"空太郎":"　ぐっと背中にかかる重さが増す。"},{"空太郎":"「……いつか、お前も乗せて飛んでやるよ」"},{"空太郎":"　首にかかる髪の毛を軽く触ると、[r]　くすぐったそうに体をよじる。"},{"空太郎":"　……教証を持っていない俺では、[r]　華子を乗せて飛ぶことはできない。"},{"空太郎":"　だから、いつか、の話しかできない。[r]　それがどうしようもなくもどかしかった。"},{"華子":"「空太郎」"},{"空太郎":"「なんだ？」"},{"華子":"「……今日、送っていって」"},{"空太郎":"「ああ、お安いご用だ」"},{"華子":"「ありがと」"},{"空太郎":"　言われなくてもそうしていた。"},{"空太郎":"　……今は、華子の傍から離れたくなかった。"}]}